sink/__init__.py
sink/_base_client.py
sink/_client.py
sink/_compat.py
sink/_constants.py
sink/_exceptions.py
sink/_files.py
sink/_models.py
sink/_qs.py
sink/_resource.py
sink/_response.py
sink/_streaming.py
sink/_types.py
sink/_version.py
sink/_wrappers.py
sink/pagination.py
sink/py.typed
sink/_utils/__init__.py
sink/_utils/_logs.py
sink/_utils/_proxy.py
sink/_utils/_streams.py
sink/_utils/_transform.py
sink/_utils/_typing.py
sink/_utils/_utils.py
sink/lib/.keep
sink/resources/__init__.py
sink/resources/binaries.py
sink/resources/cards.py
sink/resources/complex_queries.py
sink/resources/config_tools.py
sink/resources/default_path_params.py
sink/resources/docstrings.py
sink/resources/empty_body.py
sink/resources/envelopes.py
sink/resources/files.py
sink/resources/header_params.py
sink/resources/make_ambiguous_schemas_explicit.py
sink/resources/make_ambiguous_schemas_looser.py
sink/resources/method_config.py
sink/resources/openapi_formats.py
sink/resources/path_params.py
sink/resources/positional_params.py
sink/resources/query_params.py
sink/resources/resources.py
sink/resources/shared_query_params.py
sink/resources/streaming.py
sink/resources/testing.py
sink/resources/tests.py
sink/resources/tools.py
sink/resources/version_1_30_names.py
sink/resources/widgets.py
sink/resources/body_params/__init__.py
sink/resources/body_params/body_params.py
sink/resources/body_params/unions.py
sink/resources/casing/__init__.py
sink/resources/casing/casing.py
sink/resources/casing/eeoc.py
sink/resources/company/__init__.py
sink/resources/company/company.py
sink/resources/company/payments.py
sink/resources/decorator_tests/__init__.py
sink/resources/decorator_tests/decorator_tests.py
sink/resources/decorator_tests/keep_this_resource.py
sink/resources/decorator_tests/languages.py
sink/resources/deeply_nested/__init__.py
sink/resources/deeply_nested/deeply_nested.py
sink/resources/deeply_nested/level_one/__init__.py
sink/resources/deeply_nested/level_one/level_one.py
sink_pypi-1.19.0.dist-info/METADATA
sink_pypi-1.19.0.dist-info/WHEEL
sink_pypi-1.19.0.dist-info/licenses/LICENSE
sink_pypi-1.19.0.dist-info/RECORD
